traceq/__init__.py
traceq/__main__.py
traceq/cli.py
traceq/analyzer/__init__.py
traceq/analyzer/builders.py
traceq/analyzer/cli.py
traceq/analyzer/main.py
traceq/analyzer/plotters.py
traceq/analyzer/transformers.py
traceq/analyzer/types.py
traceq/api/__init__.py
traceq/api/analyzer.py
traceq/api/config.py
traceq/api/context.py
traceq/api/logger.py
traceq/api/profiler.py
traceq/common/__init__.py
traceq/common/builders.py
traceq/common/cli.py
traceq/common/file_handling.py
traceq/common/introspection.py
traceq/common/logger.py
traceq/common/synchronization.py
traceq/common/transformers.py
traceq/config/__init__.py
traceq/config/analyzer.py
traceq/config/config.py
traceq/config/logger.py
traceq/config/profiler.py
traceq/profiler/__init__.py
traceq/profiler/builders.py
traceq/profiler/cli.py
traceq/profiler/handlers.py
traceq/profiler/loaders.py
traceq/profiler/main.py
traceq/profiler/tracer.py
traceq/profiler/types.py
traceq/profiler/metrics/__init__.py
traceq/profiler/metrics/memory_usage/__init__.py
traceq/profiler/metrics/memory_usage/builders.py
traceq/profiler/metrics/memory_usage/backends/__init__.py
traceq/profiler/metrics/memory_usage/backends/kernel.py
traceq/profiler/metrics/memory_usage/backends/psutil.py
traceq/profiler/metrics/memory_usage/backends/resource.py
traceq/profiler/metrics/memory_usage/backends/tracemalloc.py
traceq/profiler/metrics/time/__init__.py
traceq/profiler/metrics/time/builders.py
traceq/profiler/metrics/time/tracer.py
traceq/profiler/metrics/time/types.py
traceq-0.0.1.dist-info/LICENSE
traceq-0.0.1.dist-info/METADATA
traceq-0.0.1.dist-info/WHEEL
traceq-0.0.1.dist-info/entry_points.txt
traceq-0.0.1.dist-info/top_level.txt
traceq-0.0.1.dist-info/RECORD
