Metadata-Version: 2.1
Name: traceq
Version: 0.0.1
Summary: A precise profiler for Python, optimized for data processing tasks in high-performance computing. Capable of sampling with metadata, using minimal instrumentation.
Home-page: http://github.com/discovery-unicamp/traceq
Author: Daniel De Lucca Fonseca
Author-email: daniel@delucca.dev
Classifier: Programming Language :: Python :: 3
Classifier: License :: OSI Approved :: MIT License
Classifier: Operating System :: OS Independent
Requires-Python: >=3.8.10
License-File: LICENSE
Requires-Dist: toml ==0.10.2
Requires-Dist: toolz ==0.12.1
Requires-Dist: loguru ==0.7.2
Requires-Dist: pydantic ==2.7.1
Requires-Dist: pandas ==1.5.3
Requires-Dist: plotly ==5.22.0
Requires-Dist: plotly-resampler ==0.10.0
Requires-Dist: kaleido ==0.2.1
Requires-Dist: msgpack ==1.0.8
